{"@context": "https://linked.art/ns/v1/linked-art.json", "about": [], "classified_as": [{"id": "http://data.duchamparchives.org/cp/object/thesaurus/dessin", "label": "Dessin", "type": "Type"}, {"id": "aat:300133025", "label": "works of art", "type": "Type"}], "crm:P104_is_subject_to": null, "crm:P57_has_number_of_parts": null, "current_keeper": null, "current_location": null, "current_owner": {"id": "http://data.duchamparchives.org/pompidou", "label": "Centre Pompidou", "type": "Group"}, "depicts": [], "id": "http://data.duchamparchives.org/cp/object/150000000079563", "identified_by": [{"classified_as": [{"id": "aat:300404670", "label": "preferred terms", "type": "Type"}, {"id": "aat:300404621", "label": "repository numbers", "type": "Type"}], "id": "http://data.duchamparchives.org/cp/object/150000000079563/object_id", "type": "Identifier", "value": "150000000079563"}, {"id": "http://data.duchamparchives.org/cp/object/150000000079563/title", "type": "Name", "value": "Toile araign\u00e9e / miroir / cloison / Moire / Portillons de m\u00e9tro / pantalons de velours"}, {"classified_as": [{"id": "aat:300312355", "label": "accession numbers", "type": "Type"}], "id": "http://data.duchamparchives.org/cp/object/150000000079563/accession", "type": "Identifier", "value": "AM 1997-98 (9)"}], "label": null, "language": [], "made_of": [], "ore:isAggregatedBy": null, "part_of": [], "produced_by": {"carried_out_by": ["http://data.duchamparchives.org/cp/object/person/9000000000065931"], "consists_of": [{"carried_out_by": [{"id": "http://data.duchamparchives.org/cp/object/person/9000000000065931", "identified_by": [{"id": "http://data.duchamparchives.org/cp/object/person/9000000000065931/name", "type": "Name", "value": "Marcel Duchamp"}], "type": "Actor"}], "classified_as": [], "id": "http://data.duchamparchives.org/cp/object/150000000079563/production/artiste", "technique": [{"id": "aat:artist", "label": "artist", "type": "Type"}], "type": "Production"}], "id": "http://data.duchamparchives.org/cp/object/150000000079563/production", "timespan": {"begin_of_the_begin": "1912-01-01T00:00:00+00:00", "end_of_the_end": "1968-01-01T00:00:00+00:00", "id": "http://data.duchamparchives.org/cp/object/150000000079563/production/timespan", "label": "1912 - 1968", "type": "TimeSpan"}, "type": "Production"}, "referred_to_by": [{"classified_as": [{"id": "aat:300028702", "label": "inscriptions", "type": "Type"}], "type": "LinguisticObject", "value": "Transcription :\nInfra mince\nToile d\u2019araign\u00e9e \u2013 pas la toile [croquis]\nmais les toiles d\u2019araign\u00e9e qui ressemblent\n\u00e0 du tissu gris-blanc.\n\nR\u00e9flexion de miroir \u2013 ou de verre \u2013\nplan\nconvexe \u2013\n\ns\u00e9paration inframince \u2013 mieux\nque cloison, parce que indique\nintervalle (pris dans un sens) et\ncloison (pris dans un autre sens) \u2013 s\u00e9paration\na les 2 sens m\u00e2le et femelle.\n\nmoire \u2013\niris\u00e9s (voir interf\u00e9rences au Palais D\u00e9couverte)\n\n\nPortillon du m\u00e9tro. \u2013 Les gens\nqui passent au tout dernier moment\ninfra mince \u2013"}, {"classified_as": [{"id": "aat:300163343", "label": "media (artists' materials)", "type": "Type"}], "type": "LinguisticObject", "value": "Encre noire sur papier \u00e0 en-t\u00eate de l'H\u00f4tel Kongen af Danmark"}, {"classified_as": [{"id": "aat:300080091", "label": "description (activity)", "type": "Type"}], "type": "LinguisticObject", "value": "Ensemble de 289 notes originales de Marcel Duchamp. Notes publi\u00e9es en fac-simil\u00e9 par Paul Matisse dans \"Marcel Duchamp, Notes\" (Paris, Centre national d'art et de culture Georges Pompidou, 1980), r\u00e9parties en 4 sections : \"Inframince\", \"Le Grand Verre\", \"Projets\" et \"Jeux de mots\".\nentre 1912 et 1968"}, {"classified_as": [{"id": "aat:300026687", "label": "acknowledgments", "type": "Type"}], "id": "http://data.duchamparchives.org/cp/object/150000000079563/credit", "type": "LinguisticObject", "value": "Dation 1997"}, {"classified_as": [{"id": "aat:300266036", "label": "dimensions", "type": "Type"}], "id": "http://data.duchamparchives.org/cp/object/150000000079563/dimensions", "type": "LinguisticObject", "value": "22,6 x 14,6 cm"}], "refers_to": [], "related": [], "representation": [{"id": "https://iiif.duchamparchives.org/image/iiif/2/9000000024834", "type": "VisualItem"}], "subject_of": [], "type": "ManMadeObject", "used_for": []}