{"@context": "https://linked.art/ns/v1/linked-art.json", "about": [], "classified_as": [{"id": "aat:300133025", "label": "works of art", "type": "Type"}, {"id": "http://data.duchamparchives.org/cp/object/thesaurus/objet", "label": "Objet", "type": "Type"}], "crm:P104_is_subject_to": null, "crm:P57_has_number_of_parts": null, "current_keeper": null, "current_location": null, "current_owner": {"id": "http://data.duchamparchives.org/pompidou", "label": "Centre Pompidou", "type": "Group"}, "depicts": [], "id": "http://data.duchamparchives.org/cp/object/150000000013868", "identified_by": [{"classified_as": [{"id": "aat:300404670", "label": "preferred terms", "type": "Type"}, {"id": "aat:300404621", "label": "repository numbers", "type": "Type"}], "id": "http://data.duchamparchives.org/cp/object/150000000013868/object_id", "type": "Identifier", "value": "150000000013868"}, {"classified_as": [{"id": "aat:300312355", "label": "accession numbers", "type": "Type"}], "id": "http://data.duchamparchives.org/cp/object/150000000013868/accession", "type": "Identifier", "value": "AM 1976-1188"}, {"id": "http://data.duchamparchives.org/cp/object/150000000013868/title", "type": "Name", "value": "La Bo\u00eete alerte"}], "label": null, "language": [], "made_of": [], "ore:isAggregatedBy": null, "part_of": [], "produced_by": {"carried_out_by": ["http://data.duchamparchives.org/cp/object/person/150000001036284", "http://data.duchamparchives.org/cp/object/person/9000000000065931"], "consists_of": [{"carried_out_by": [{"id": "http://data.duchamparchives.org/cp/object/person/150000001036284", "identified_by": [{"id": "http://data.duchamparchives.org/cp/object/person/150000001036284/name", "type": "Name", "value": "Mimi Parent"}], "type": "Actor"}, {"id": "http://data.duchamparchives.org/cp/object/person/9000000000065931", "identified_by": [{"id": "http://data.duchamparchives.org/cp/object/person/9000000000065931/name", "type": "Name", "value": "Marcel Duchamp"}], "type": "Actor"}], "classified_as": [], "id": "http://data.duchamparchives.org/cp/object/150000000013868/production/artiste", "technique": [{"id": "aat:artist", "label": "artist", "type": "Type"}], "type": "Production"}], "id": "http://data.duchamparchives.org/cp/object/150000000013868/production", "timespan": {"begin_of_the_begin": "1959-01-01T00:00:00+00:00", "end_of_the_end": "1960-01-01T00:00:00+00:00", "id": "http://data.duchamparchives.org/cp/object/150000000013868/production/timespan", "label": "1959 - 1960", "type": "TimeSpan"}, "type": "Production"}, "referred_to_by": [{"classified_as": [{"id": "aat:300028702", "label": "inscriptions", "type": "Type"}], "type": "LinguisticObject", "value": "Sur le flanc de la bo\u00eete : Exposition Internationale du Surr\u00e9alisme, en blanc sur fond vert, les lettres E, R, O et S (Eros) se d\u00e9tachant en rouge."}, {"classified_as": [{"id": "aat:300026687", "label": "acknowledgments", "type": "Type"}], "id": "http://data.duchamparchives.org/cp/object/150000000013868/credit", "type": "LinguisticObject", "value": "Don de M. Daniel Cordier 1976"}, {"classified_as": [{"id": "aat:300266036", "label": "dimensions", "type": "Type"}], "id": "http://data.duchamparchives.org/cp/object/150000000013868/dimensions", "type": "LinguisticObject", "value": "28 x 17,9 x 6,4 cm"}, {"classified_as": [{"id": "aat:300163343", "label": "media (artists' materials)", "type": "Type"}], "type": "LinguisticObject", "value": "Bo\u00eete \u00e0 lettre en carton contenant :\n. le catalogue de l'Exposition internationale du surr\u00e9alisme (galerie Daniel Cordier) ;\n. 9 enveloppes, dont 6 sont timbr\u00e9es. L'une de ces enveloppes contient un bas noir marqu\u00e9 \"HAUT\", une autre contient une d\u00e9calcomanie originale de Micheline Bounoure, les autres enveloppes renferment une reproduction de lettre, un d\u00e9pliant, des feuillets imprim\u00e9s, enfin plusieurs livrets ;\n. un t\u00e9l\u00e9gramme sign\u00e9 \"Rrose\", adress\u00e9 \u00e0 Andr\u00e9 Breton ;\n. 6 cartes postales ;\n. un portfolio de 5 estampes de Dax, Svanberg, Miro, Toyen, Mar\u00e9chal, toutes num\u00e9rot\u00e9es IX/XX ;\n. un disque 45 tours (interpr\u00e9tations enregistr\u00e9es de deux textes, de Joyce Mansour et Benjamin P\u00e9ret) ;\n. un ready-made de Marcel Duchamp : Couple de tabliers.\nCarton, papier, calque, timbres, tissu, lithographies, disque vinyle"}], "refers_to": [], "related": [], "representation": [{"id": "https://iiif.duchamparchives.org/image/iiif/2/90000000355143", "type": "VisualItem"}], "subject_of": [], "type": "ManMadeObject", "used_for": []}