{"@context": "https://linked.art/ns/v1/linked-art.json", "about": [], "classified_as": [{"id": "aat:object", "label": "object", "type": "Type"}, {"id": "aat:300189226", "label": "writings (documents)", "type": "Type"}, {"id": "aat:300375748", "label": "archives (groupings)", "type": "Type"}], "crm:P104_is_subject_to": [{"classified_as": [{"id": "aat:300417633", "label": "legal status", "type": "Type"}], "id": "_:b5", "type": "crm:E30_Right"}, {"classified_as": [{"id": "aat:300068844", "label": "use", "type": "Type"}], "id": "_:b4", "type": "crm:E30_Right"}], "crm:P57_has_number_of_parts": null, "current_keeper": null, "current_location": {"label": "Philadelphia Museum of Art, Library & Archives", "type": "Place"}, "current_owner": {"id": "http://data.philamuseum.org/", "label": "Philadelphia Museum of Art", "type": "Group"}, "depicts": [], "id": "http://data.duchamparchives.org/pma/archive/component/MDE_B007_F031_001", "identified_by": [{"classified_as": [{"id": "aat:300404670", "label": "preferred terms", "type": "Type"}], "id": "http://data.duchamparchives.org/pma/archive/component/aspace_adc0451c81d6db646be6dea6714f2ae2/id", "type": "Identifier", "value": "aspace_adc0451c81d6db646be6dea6714f2ae2"}, {"id": "http://data.duchamparchives.org/pma/archive/component/aspace_adc0451c81d6db646be6dea6714f2ae2/unittitle", "type": "Name", "value": "Marcel Duchamp and Andr\u00e9 Breton"}, {"classified_as": [{"id": "aat:box", "label": "box", "type": "Type"}], "id": "http://data.duchamparchives.org/pma/archive/container/aspace_0f579500fd9a008aa1c264ce3825c3c9", "label": "Mixed Materials", "type": "Identifier", "value": "7"}, {"classified_as": [{"id": "aat:folder", "label": "folder", "type": "Type"}], "id": "http://data.duchamparchives.org/pma/archive/container/aspace_c99bb053fc674bd016ed01e8f4bfd590", "type": "Identifier", "value": "31"}, {"classified_as": [{"id": "aat:accession", "label": "accession", "type": "Type"}], "id": "http://data.duchamparchives.org/pma/archive/component/aspace_adc0451c81d6db646be6dea6714f2ae2/unitid/0", "type": "Identifier", "value": "MDE_B007_F031_001"}, {"classified_as": [{"id": "aat:300192339", "label": "sequences", "type": "Type"}], "type": "Identifier", "value": "0"}], "label": null, "language": [{"id": "aat:300388277", "label": "English (language)", "type": "Type"}], "made_of": [], "ore:isAggregatedBy": null, "part_of": [{"classified_as": [{"id": "aat:300375748", "label": "archives (groupings)", "type": "Type"}, {"id": "aat:series", "label": "series", "type": "Type"}], "id": "http://data.duchamparchives.org/pma/archive/component/aspace_s32", "identified_by": [{"classified_as": [{"id": "aat:300404670", "label": "preferred terms", "type": "Type"}], "id": "http://data.duchamparchives.org/pma/archive/component/aspace_s32/id", "type": "Identifier", "value": "aspace_s32"}, {"classified_as": [{"id": "aat:300192339", "label": "sequences", "type": "Type"}], "id": "_:b797", "type": "Identifier", "value": "1"}, {"id": "http://data.duchamparchives.org/pma/archive/component/aspace_s32/unittitle", "type": "Name", "value": "Philadelphia Museum of Art, \"Marcel Duchamp,\" 1973"}], "part": ["http://data.duchamparchives.org/pma/archive/component/aspace_ss76", "http://data.duchamparchives.org/pma/archive/component/aspace_d4de0c1c9716b9822889cd730ed6a93d", "http://data.duchamparchives.org/pma/archive/component/aspace_1e06e4ec95035826fb110eba47c1879c", "http://data.duchamparchives.org/pma/archive/component/aspace_ss77", "http://data.duchamparchives.org/pma/archive/component/aspace_dfbcaa0d5692382c8fc1f98a8cfd0ff3", "http://data.duchamparchives.org/pma/archive/component/aspace_ss73", "http://data.duchamparchives.org/pma/archive/component/aspace_ss78", "http://data.duchamparchives.org/pma/archive/component/aspace_ss91", "http://data.duchamparchives.org/pma/archive/component/aspace_8424455b03aeddef70ce70b1897cd522", "http://data.duchamparchives.org/pma/archive/component/aspace_cea8a4f69f64c44170338cb16ab391bc"], "type": "PhysicalObject"}, {"classified_as": [{"id": "aat:300375748", "label": "archives (groupings)", "type": "Type"}, {"id": "aat:file", "label": "file", "type": "Type"}], "id": "http://data.duchamparchives.org/pma/archive/component/aspace_7efa904761cc59681ae147e3c6dd7a24", "identified_by": [{"classified_as": [{"id": "aat:folder", "label": "folder", "type": "Type"}], "id": "http://data.duchamparchives.org/pma/archive/container/aspace_3d55536ee3ed6f6bc86b1d8e44e2e2e1", "type": "Identifier", "value": "31"}, {"classified_as": [{"id": "aat:300404670", "label": "preferred terms", "type": "Type"}], "id": "http://data.duchamparchives.org/pma/archive/component/aspace_7efa904761cc59681ae147e3c6dd7a24/id", "type": "Identifier", "value": "aspace_7efa904761cc59681ae147e3c6dd7a24"}, {"classified_as": [{"id": "aat:300192339", "label": "sequences", "type": "Type"}], "type": "Identifier", "value": "2"}, {"id": "http://data.duchamparchives.org/pma/archive/component/aspace_7efa904761cc59681ae147e3c6dd7a24/unittitle", "type": "Name", "value": "Lebel, Robert. \"Marcel Duchamp and Andr\u00e9 Breton.\""}, {"classified_as": [{"id": "aat:box", "label": "box", "type": "Type"}], "id": "http://data.duchamparchives.org/pma/archive/container/aspace_a2b11c24943315d5b36d3d43e31d1e55", "label": "Mixed Materials", "type": "Identifier", "value": "7"}], "part": ["http://data.duchamparchives.org/pma/archive/component/MDE_B007_F031_002", "http://data.duchamparchives.org/pma/archive/component/MDE_B007_F031_001"], "type": "PhysicalObject"}, {"classified_as": [{"id": "aat:collection", "label": "collection", "type": "Type"}, {"id": "aat:300375748", "label": "archives (groupings)", "type": "Type"}], "id": "http://data.duchamparchives.org/pma/archive/collection/marcel-duchamp-exhibition-records", "identified_by": [{"classified_as": [{"id": "aat:300404670", "label": "preferred terms", "type": "Type"}], "id": "_:b15", "type": "Name", "value": "Marcel Duchamp Exhibition Records"}, {"classified_as": [{"id": "aat:accession", "label": "accession", "type": "Type"}], "id": "_:b16", "type": "Identifier", "value": "MDE"}], "part": ["http://data.duchamparchives.org/pma/archive/component/aspace_s29", "http://data.duchamparchives.org/pma/archive/component/aspace_s27", "http://data.duchamparchives.org/pma/archive/component/aspace_s44", "http://data.duchamparchives.org/pma/archive/component/aspace_s26", "http://data.duchamparchives.org/pma/archive/component/aspace_s31", "http://data.duchamparchives.org/pma/archive/component/aspace_s28", "http://data.duchamparchives.org/pma/archive/component/aspace_s32", "http://data.duchamparchives.org/pma/archive/component/aspace_s30"], "type": "PhysicalObject"}, {"classified_as": [{"id": "aat:subseries", "label": "subseries", "type": "Type"}, {"id": "aat:300375748", "label": "archives (groupings)", "type": "Type"}], "id": "http://data.duchamparchives.org/pma/archive/component/aspace_ss76", "identified_by": [{"classified_as": [{"id": "aat:300404670", "label": "preferred terms", "type": "Type"}], "id": "http://data.duchamparchives.org/pma/archive/component/aspace_ss76/id", "type": "Identifier", "value": "aspace_ss76"}, {"id": "http://data.duchamparchives.org/pma/archive/component/aspace_ss76/unittitle", "type": "Name", "value": "Catalog"}, {"classified_as": [{"id": "aat:300192339", "label": "sequences", "type": "Type"}], "id": "_:b848", "type": "Identifier", "value": "2"}], "part": ["http://data.duchamparchives.org/pma/archive/component/aspace_7a3be2df27aef20c2e77e5fd75ff9a16", "http://data.duchamparchives.org/pma/archive/component/aspace_3f39980bcb3c02774362bcaa3e919f1b", "http://data.duchamparchives.org/pma/archive/component/aspace_f4293864d716e9f16d4e63ee5b0489f8", "http://data.duchamparchives.org/pma/archive/component/aspace_9aac5ae5454627764ed4afdefda5632f", "http://data.duchamparchives.org/pma/archive/component/aspace_c4d86b5c8ed4f10de6564ee0e5f77a1c", "http://data.duchamparchives.org/pma/archive/component/aspace_598e5a3d3b160be3aef98a2ea3f992fb"], "type": "PhysicalObject"}, {"classified_as": [{"id": "aat:300375748", "label": "archives (groupings)", "type": "Type"}, {"id": "aat:subseries", "label": "subseries", "type": "Type"}], "id": "http://data.duchamparchives.org/pma/archive/component/aspace_c4d86b5c8ed4f10de6564ee0e5f77a1c", "identified_by": [{"id": "http://data.duchamparchives.org/pma/archive/component/aspace_c4d86b5c8ed4f10de6564ee0e5f77a1c/unittitle", "type": "Name", "value": "Essays"}, {"classified_as": [{"id": "aat:300404670", "label": "preferred terms", "type": "Type"}], "id": "http://data.duchamparchives.org/pma/archive/component/aspace_c4d86b5c8ed4f10de6564ee0e5f77a1c/id", "type": "Identifier", "value": "aspace_c4d86b5c8ed4f10de6564ee0e5f77a1c"}, {"classified_as": [{"id": "aat:300192339", "label": "sequences", "type": "Type"}], "id": "_:b146", "type": "Identifier", "value": "1"}], "part": ["http://data.duchamparchives.org/pma/archive/component/aspace_7efa904761cc59681ae147e3c6dd7a24", "http://data.duchamparchives.org/pma/archive/component/aspace_eabb40d10c15b63c7fdae11584da6a10", "http://data.duchamparchives.org/pma/archive/component/aspace_03d7119db2d480da3ea936c1ae1329fd", "http://data.duchamparchives.org/pma/archive/component/aspace_284fd9c484ce0f3019b9a18758cb88e6", "http://data.duchamparchives.org/pma/archive/component/aspace_57b96028c7d0c265b3a82806f68b8357", "http://data.duchamparchives.org/pma/archive/component/aspace_d055dfa8c3864efa798a6564063ceb66", "http://data.duchamparchives.org/pma/archive/component/aspace_d1e483b506648ba17b2fc50bd5e2bb20", "http://data.duchamparchives.org/pma/archive/component/aspace_0c1b56cdec3d6cb6a25ffe9c50b41240", "http://data.duchamparchives.org/pma/archive/component/aspace_326831a5323e3c4eff92e724d1f9ab9d", "http://data.duchamparchives.org/pma/archive/component/aspace_fa2c12563712917f18971d1bf033964b", "http://data.duchamparchives.org/pma/archive/component/aspace_45131c30b72f696c414c020be2d44893"], "type": "PhysicalObject"}], "produced_by": {"carried_out_by": ["http://data.duchamparchives.org/pma/archive/actor/LCNAF/n84020233"], "consists_of": [{"carried_out_by": [{"id": "http://data.duchamparchives.org/pma/archive/actor/LCNAF/n80057220", "label": "Duchamp, Marcel, 1887-1968", "type": "Actor"}, {"id": "http://data.duchamparchives.org/pma/archive/actor/LCNAF/n50019704", "label": "Picabia, Francis, 1879-1953", "type": "Actor"}, {"id": "http://data.duchamparchives.org/pma/archive/actor/LCNAF/n80036675", "label": "Breton, Andr\u00e9, 1896-1966", "type": "Actor"}, {"id": "http://data.duchamparchives.org/pma/archive/actor/LCNAF/n79006797", "label": "Deleuze, Gilles, 1925-1995", "type": "Actor"}, {"id": "http://data.duchamparchives.org/pma/archive/actor/LCNAF/n50021770", "label": "Roussel, Raymond, 1877-1933", "type": "Actor"}, {"id": "http://data.duchamparchives.org/pma/archive/actor/LCNAF/n79069950", "label": "De Chirico, Giorgio, 1888-1978", "type": "Actor"}, {"id": "http://data.duchamparchives.org/pma/archive/actor/LCNAF/n79138845", "label": "Guattari, F\u00e9lix, 1930-1992", "type": "Actor"}, {"id": "http://data.duchamparchives.org/pma/archive/actor/LCNAF/n80019625", "label": "Man Ray, 1890-1976", "type": "Actor"}, {"id": "http://data.duchamparchives.org/pma/archive/actor/LCNAF/n83214080", "label": "Vach\u00e9, Jacques", "type": "Actor"}, {"id": "http://data.duchamparchives.org/pma/archive/actor/LCNAF/n79144795", "label": "Ernst, Max, 1891-1976", "type": "Actor"}, {"id": "http://data.duchamparchives.org/pma/archive/actor/LCNAF/n79099210", "label": "Laforgue, Jules, 1860-1887", "type": "Actor"}, {"id": "http://data.duchamparchives.org/pma/archive/actor/LCNAF/n78080654", "label": "Apollinaire, Guillaume, 1880-1918", "type": "Actor"}, {"id": "http://data.duchamparchives.org/pma/archive/actor/LCNAF/n80005093", "label": "Val\u00e9ry, Paul, 1871-1945", "type": "Actor"}, {"id": "http://data.duchamparchives.org/pma/archive/actor/LCNAF/n50001632", "label": "Desnos, Robert, 1900-1945", "type": "Actor"}, {"id": "http://data.duchamparchives.org/pma/archive/actor/LCNAF/n78086005", "label": "Picasso, Pablo, 1881-1973", "type": "Actor"}, {"id": "http://data.duchamparchives.org/pma/archive/actor/LCNAF/n79045066", "label": "Mallarm\u00e9, St\u00e9phane, 1842-1898", "type": "Actor"}], "classified_as": [], "id": "http://data.duchamparchives.org/pma/archive/component/aspace_adc0451c81d6db646be6dea6714f2ae2/production/referenced", "technique": [{"id": "aat:referenced", "label": "referenced", "type": "Type"}], "type": "Production"}, {"carried_out_by": [{"id": "http://data.duchamparchives.org/pma/archive/actor/LCNAF/n84020233", "label": "Lebel, Robert", "type": "Actor"}], "classified_as": [], "id": "http://data.duchamparchives.org/pma/archive/component/aspace_adc0451c81d6db646be6dea6714f2ae2/production/aut", "technique": [{"id": "aat:author", "label": "author", "type": "Type"}], "type": "Production"}], "id": "http://data.duchamparchives.org/pma/archive/component/aspace_adc0451c81d6db646be6dea6714f2ae2/production", "timespan": {"begin_of_the_begin": "1972-01-01T00:00:00+00:00", "end_of_the_end": "1973-01-01T00:00:00+00:00", "id": "http://data.duchamparchives.org/pma/archive/component/aspace_adc0451c81d6db646be6dea6714f2ae2/production/timespan", "label": "circa 1972-1973", "type": "TimeSpan"}, "type": "Production"}, "referred_to_by": [{"classified_as": ["aat:scopenote"], "id": "http://data.duchamparchives.org/pma/archive/component/aspace_adc0451c81d6db646be6dea6714f2ae2/scope", "type": "LinguisticObject", "value": "&lt;p&gt;Lebel, Robert. \"Marcel Duchamp and Andr\u00e9 Breton.\"&lt;/p&gt;"}, {"classified_as": ["aat:related"], "type": "LinguisticObject", "value": "The Bride Stripped Bare by Her Bachelors, Even (The Large Glass);\nThe Bride Stripped Bare by Her Bachelors, Even (The Green Box);\nBride"}, {"classified_as": [{"id": "aat:300266036", "label": "dimensions", "type": "Type"}], "type": "LinguisticObject", "value": "6 pages"}], "refers_to": [], "related": [], "representation": [{"id": "https://iiif.duchamparchives.org/image/iiif/2/MDE_B007_F031_001_001", "type": "VisualItem"}, {"id": "https://iiif.duchamparchives.org/image/iiif/2/MDE_B007_F031_001_002", "type": "VisualItem"}, {"id": "https://iiif.duchamparchives.org/image/iiif/2/MDE_B007_F031_001_003", "type": "VisualItem"}, {"id": "https://iiif.duchamparchives.org/image/iiif/2/MDE_B007_F031_001_004", "type": "VisualItem"}, {"id": "https://iiif.duchamparchives.org/image/iiif/2/MDE_B007_F031_001_005", "type": "VisualItem"}, {"id": "https://iiif.duchamparchives.org/image/iiif/2/MDE_B007_F031_001_006", "type": "VisualItem"}], "subject_of": [], "type": "ManMadeObject", "used_for": []}