{"@context": "https://linked.art/ns/v1/linked-art.json", "about": [], "classified_as": [{"id": "aat:object", "label": "object", "type": "Type"}, {"id": "aat:300026867", "label": "clippings (information artifacts)", "type": "Type"}, {"id": "aat:300375748", "label": "archives (groupings)", "type": "Type"}], "crm:P104_is_subject_to": [{"classified_as": [{"id": "aat:300068844", "label": "use", "type": "Type"}], "id": "_:b1", "type": "crm:E30_Right"}, {"classified_as": [{"id": "aat:300417633", "label": "legal status", "type": "Type"}], "id": "_:b0", "type": "crm:E30_Right"}], "crm:P57_has_number_of_parts": null, "current_keeper": null, "current_location": {"label": "Philadelphia Museum of Art, Library & Archives", "type": "Place"}, "current_owner": {"id": "http://data.philamuseum.org/", "label": "Philadelphia Museum of Art", "type": "Group"}, "depicts": [], "id": "http://data.duchamparchives.org/pma/archive/component/MDE_B026_F058_001", "identified_by": [{"id": "http://data.duchamparchives.org/pma/archive/component/aspace_fb370e44446b29d1b66d2580b2e7b5e3/unittitle", "type": "Name", "value": "The Globe and Mail. \"Duchamp: Almost 20 years after the artist's death, the arguments rage -- this time for 3 days\""}, {"classified_as": [{"id": "aat:box", "label": "box", "type": "Type"}], "id": "http://data.duchamparchives.org/pma/archive/container/aspace_2f1a03d34852457ceb0d2f8ed90428d3", "label": "Mixed Materials", "type": "Identifier", "value": "26"}, {"classified_as": [{"id": "aat:accession", "label": "accession", "type": "Type"}], "id": "http://data.duchamparchives.org/pma/archive/component/aspace_fb370e44446b29d1b66d2580b2e7b5e3/unitid/0", "type": "Identifier", "value": "MDE_B026_F058_001"}, {"classified_as": [{"id": "aat:300192339", "label": "sequences", "type": "Type"}], "type": "Identifier", "value": "0"}, {"classified_as": [{"id": "aat:folder", "label": "folder", "type": "Type"}], "id": "http://data.duchamparchives.org/pma/archive/container/aspace_f44886045d13a1835980e0429b5d6d54", "type": "Identifier", "value": "58"}, {"classified_as": [{"id": "aat:300404670", "label": "preferred terms", "type": "Type"}], "id": "http://data.duchamparchives.org/pma/archive/component/aspace_fb370e44446b29d1b66d2580b2e7b5e3/id", "type": "Identifier", "value": "aspace_fb370e44446b29d1b66d2580b2e7b5e3"}], "label": null, "language": [{"id": "aat:300388277", "label": "English (language)", "type": "Type"}], "made_of": [], "ore:isAggregatedBy": null, "part_of": [{"classified_as": [{"id": "aat:collection", "label": "collection", "type": "Type"}, {"id": "aat:300375748", "label": "archives (groupings)", "type": "Type"}], "id": "http://data.duchamparchives.org/pma/archive/collection/marcel-duchamp-exhibition-records", "identified_by": [{"classified_as": [{"id": "aat:accession", "label": "accession", "type": "Type"}], "id": "_:b38", "type": "Identifier", "value": "MDE"}, {"classified_as": [{"id": "aat:300404670", "label": "preferred terms", "type": "Type"}], "id": "_:b39", "type": "Name", "value": "Marcel Duchamp Exhibition Records"}], "part": ["http://data.duchamparchives.org/pma/archive/component/aspace_s28", "http://data.duchamparchives.org/pma/archive/component/aspace_s26", "http://data.duchamparchives.org/pma/archive/component/aspace_s44", "http://data.duchamparchives.org/pma/archive/component/aspace_s29", "http://data.duchamparchives.org/pma/archive/component/aspace_s31", "http://data.duchamparchives.org/pma/archive/component/aspace_s27", "http://data.duchamparchives.org/pma/archive/component/aspace_s32", "http://data.duchamparchives.org/pma/archive/component/aspace_s30"], "type": "PhysicalObject"}, {"classified_as": [{"id": "aat:series", "label": "series", "type": "Type"}, {"id": "aat:300375748", "label": "archives (groupings)", "type": "Type"}], "id": "http://data.duchamparchives.org/pma/archive/component/aspace_s31", "identified_by": [{"classified_as": [{"id": "aat:300404670", "label": "preferred terms", "type": "Type"}], "id": "http://data.duchamparchives.org/pma/archive/component/aspace_s31/id", "type": "Identifier", "value": "aspace_s31"}, {"classified_as": [{"id": "aat:300192339", "label": "sequences", "type": "Type"}], "id": "_:b247", "type": "Identifier", "value": "5"}, {"id": "http://data.duchamparchives.org/pma/archive/component/aspace_s31/unittitle", "type": "Name", "value": "Philadelphia Museum of Art, \"A propos of Duchamp,\" 1987"}], "part": ["http://data.duchamparchives.org/pma/archive/component/aspace_eb86eac7668b768c8ae9ab876bc567b5", "http://data.duchamparchives.org/pma/archive/component/aspace_255693429edfe144596d427da68a9a00", "http://data.duchamparchives.org/pma/archive/component/aspace_05bdc76fe180ca2feb39f65b7ed24298", "http://data.duchamparchives.org/pma/archive/component/aspace_ss123", "http://data.duchamparchives.org/pma/archive/component/aspace_00e8a9476e1c36988d10052636a2456a", "http://data.duchamparchives.org/pma/archive/component/aspace_ac46c864f118c61e66e671fbdcbd20ed"], "type": "PhysicalObject"}, {"classified_as": [{"id": "aat:subseries", "label": "subseries", "type": "Type"}, {"id": "aat:300375748", "label": "archives (groupings)", "type": "Type"}], "id": "http://data.duchamparchives.org/pma/archive/component/aspace_255693429edfe144596d427da68a9a00", "identified_by": [{"classified_as": [{"id": "aat:300192339", "label": "sequences", "type": "Type"}], "id": "_:b571", "type": "Identifier", "value": "4"}, {"classified_as": [{"id": "aat:300404670", "label": "preferred terms", "type": "Type"}], "id": "http://data.duchamparchives.org/pma/archive/component/aspace_255693429edfe144596d427da68a9a00/id", "type": "Identifier", "value": "aspace_255693429edfe144596d427da68a9a00"}, {"id": "http://data.duchamparchives.org/pma/archive/component/aspace_255693429edfe144596d427da68a9a00/unittitle", "type": "Name", "value": "Clippings"}], "part": ["http://data.duchamparchives.org/pma/archive/component/aspace_4a4e6c66a5d2c7fed4bf3bf6fa5e8892", "http://data.duchamparchives.org/pma/archive/component/aspace_beeb9a278e3782bb8201b9e879052da1", "http://data.duchamparchives.org/pma/archive/component/aspace_9329c6a9f7c9af929206debdc6d8a01f", "http://data.duchamparchives.org/pma/archive/component/aspace_e114df28f78f4f483c077c728f975916", "http://data.duchamparchives.org/pma/archive/component/aspace_e799d8a0d9946e0ee89cd67a96ed214a", "http://data.duchamparchives.org/pma/archive/component/aspace_eaee7af5629dc2656be683b9498baeaf", "http://data.duchamparchives.org/pma/archive/component/aspace_c10b461aac30e06d90f411783f945dc4", "http://data.duchamparchives.org/pma/archive/component/aspace_078b32fdaed139347fd716becab6fec4", "http://data.duchamparchives.org/pma/archive/component/aspace_c422b9e6b1d3be949fdf3e91adcde041", "http://data.duchamparchives.org/pma/archive/component/aspace_f44fb9ee8fa41d4b9f63593ad873d602", "http://data.duchamparchives.org/pma/archive/component/aspace_468d3ebb6230c2d42790d234ca0f98fa", "http://data.duchamparchives.org/pma/archive/component/aspace_60486a908e709860f9df14c837b476cb", "http://data.duchamparchives.org/pma/archive/component/aspace_f7832e4124a457d66569f1520dc97a35"], "type": "PhysicalObject"}, {"classified_as": [{"id": "aat:file", "label": "file", "type": "Type"}, {"id": "aat:300375748", "label": "archives (groupings)", "type": "Type"}], "id": "http://data.duchamparchives.org/pma/archive/component/aspace_eaee7af5629dc2656be683b9498baeaf", "identified_by": [{"classified_as": [{"id": "aat:300192339", "label": "sequences", "type": "Type"}], "type": "Identifier", "value": "6"}, {"id": "http://data.duchamparchives.org/pma/archive/component/aspace_eaee7af5629dc2656be683b9498baeaf/unittitle", "type": "Name", "value": "Nova Scotia College of Art and Design. Marcel Duchamp conference. Review"}, {"classified_as": [{"id": "aat:300404670", "label": "preferred terms", "type": "Type"}], "id": "http://data.duchamparchives.org/pma/archive/component/aspace_eaee7af5629dc2656be683b9498baeaf/id", "type": "Identifier", "value": "aspace_eaee7af5629dc2656be683b9498baeaf"}, {"classified_as": [{"id": "aat:box", "label": "box", "type": "Type"}], "id": "http://data.duchamparchives.org/pma/archive/container/aspace_bbe7008afc79e491f7ba633fbaf239dd", "label": "Mixed Materials", "type": "Identifier", "value": "26"}, {"classified_as": [{"id": "aat:folder", "label": "folder", "type": "Type"}], "id": "http://data.duchamparchives.org/pma/archive/container/aspace_6bfc32116832672b772dacfe238ae148", "type": "Identifier", "value": "58"}], "part": "http://data.duchamparchives.org/pma/archive/component/MDE_B026_F058_001", "type": "PhysicalObject"}], "produced_by": {"carried_out_by": ["http://data.duchamparchives.org/pma/archive/actor/LCNAF/n78052711", "http://data.duchamparchives.org/pma/archive/actor/LCNAF/nr89010035"], "consists_of": [{"carried_out_by": [{"id": "http://data.duchamparchives.org/pma/archive/actor/LCNAF/nr89010035", "label": "Globe and Mail (Firm)", "type": "Actor"}], "classified_as": [], "id": "http://data.duchamparchives.org/pma/archive/component/aspace_fb370e44446b29d1b66d2580b2e7b5e3/production/cre", "technique": [{"id": "aat:300386174", "label": "creators", "type": "Type"}], "type": "Production"}, {"carried_out_by": [{"id": "http://data.duchamparchives.org/pma/archive/actor/LCNAF/n80057220", "label": "Duchamp, Marcel, 1887-1968", "type": "Actor"}, {"id": "http://data.duchamparchives.org/pma/archive/actor/LCNAF/n91069550", "label": "Nesbit, Molly, 1952-", "type": "Actor"}, {"id": "http://data.duchamparchives.org/pma/archive/actor/LCNAF/n81068990", "label": "Molderings, Herbert", "type": "Actor"}, {"id": "http://data.duchamparchives.org/pma/archive/actor/LCNAF/n84193736", "label": "Duve, Thierry de", "type": "Actor"}, {"id": "http://data.duchamparchives.org/pma/archive/actor/LCNAF/n50044024", "label": "Krauss, Rosalind E.", "type": "Actor"}, {"id": "http://data.duchamparchives.org/pma/archive/actor/LCNAF/n83148694", "label": "Adcock, Craig E.", "type": "Actor"}, {"id": "http://data.duchamparchives.org/pma/archive/actor/LCNAF/n91069076", "label": "Suquet, Jean", "type": "Actor"}, {"id": "http://data.duchamparchives.org/pma/archive/actor/young-h-dennis", "label": "Young, H. Dennis", "type": "Actor"}], "classified_as": [], "id": "http://data.duchamparchives.org/pma/archive/component/aspace_fb370e44446b29d1b66d2580b2e7b5e3/production/referenced", "technique": [{"id": "aat:referenced", "label": "referenced", "type": "Type"}], "type": "Production"}, {"carried_out_by": [{"id": "http://data.duchamparchives.org/pma/archive/actor/LCNAF/n78052711", "label": "Mays, John Bentley", "type": "Actor"}], "classified_as": [], "id": "http://data.duchamparchives.org/pma/archive/component/aspace_fb370e44446b29d1b66d2580b2e7b5e3/production/aut", "technique": [{"id": "aat:author", "label": "author", "type": "Type"}], "type": "Production"}], "id": "http://data.duchamparchives.org/pma/archive/component/aspace_fb370e44446b29d1b66d2580b2e7b5e3/production", "timespan": {"begin_of_the_begin": "1987-01-01T00:00:00+00:00", "end_of_the_end": "1987-01-01T00:00:00+00:00", "id": "http://data.duchamparchives.org/pma/archive/component/aspace_fb370e44446b29d1b66d2580b2e7b5e3/production/timespan", "label": "1987 October 10", "type": "TimeSpan"}, "took_place_at": [{"id": "ttp://vocab.getty.edu/tgn/7013046", "label": "Halifax, Canada", "type": "Place"}], "type": "Production"}, "referred_to_by": [{"classified_as": ["aat:scopenote"], "id": "http://data.duchamparchives.org/pma/archive/component/aspace_fb370e44446b29d1b66d2580b2e7b5e3/scope", "type": "LinguisticObject", "value": "&lt;p&gt;The Globe and Mail. \"Duchamp: Almost 20 years after the artist's death, the arguments rage -- this time for 3 days\" by John Bentley Mays [copy].&lt;/p&gt;"}, {"classified_as": [{"id": "aat:300133046", "label": "access", "type": "Type"}], "type": "LinguisticObject", "value": "This item is accessible onsite at the Philadelphia Museum of Art. Please contact archives@philamuseum.org to make an appointment."}, {"classified_as": [{"id": "aat:300266036", "label": "dimensions", "type": "Type"}], "type": "LinguisticObject", "value": "2 pages"}, {"classified_as": ["aat:related"], "type": "LinguisticObject", "value": "Nude Descending a Staircase (No. 2);\nFountain;\nThe Bride Stripped Bare by Her Bachelors, Even (The Large Glass)"}], "refers_to": [], "related": [], "representation": [], "subject_of": [], "type": "ManMadeObject", "used_for": []}