{"@context": "https://linked.art/ns/v1/linked-art.json", "about": [], "classified_as": [{"id": "aat:300128695", "label": "gelatin silver prints", "type": "Type"}, {"id": "aat:300375748", "label": "archives (groupings)", "type": "Type"}, {"id": "aat:object", "label": "object", "type": "Type"}], "crm:P104_is_subject_to": [{"classified_as": [{"id": "aat:300068844", "label": "use", "type": "Type"}], "id": "_:b0", "type": "crm:E30_Right"}, {"classified_as": [{"id": "aat:300417633", "label": "legal status", "type": "Type"}], "id": "_:b1", "type": "crm:E30_Right"}], "crm:P57_has_number_of_parts": null, "current_keeper": null, "current_location": {"label": "Philadelphia Museum of Art, Library & Archives", "type": "Place"}, "current_owner": {"id": "http://data.philamuseum.org/", "label": "Philadelphia Museum of Art", "type": "Group"}, "depicts": [], "id": "http://data.duchamparchives.org/pma/archive/component/MDP_B034_F015_13-1972-9-170", "identified_by": [{"classified_as": [{"id": "aat:300192339", "label": "sequences", "type": "Type"}], "type": "Identifier", "value": "0"}, {"classified_as": [{"id": "aat:300404670", "label": "preferred terms", "type": "Type"}], "id": "http://data.duchamparchives.org/pma/archive/component/aspace_baaafb5813cdff528e1ac5db1497b73a/id", "type": "Identifier", "value": "aspace_baaafb5813cdff528e1ac5db1497b73a"}, {"classified_as": [{"id": "aat:accession", "label": "accession", "type": "Type"}], "id": "http://data.duchamparchives.org/pma/archive/component/aspace_baaafb5813cdff528e1ac5db1497b73a/unitid/0", "type": "Identifier", "value": "MDP_B034_F015_13-1972-9-170"}, {"classified_as": [{"id": "aat:box", "label": "box", "type": "Type"}], "id": "http://data.duchamparchives.org/pma/archive/container/aspace_0e5c230abdb736e435eec76d8cc0298e", "label": "Mixed Materials", "type": "Identifier", "value": "34"}, {"id": "http://data.duchamparchives.org/pma/archive/component/aspace_baaafb5813cdff528e1ac5db1497b73a/unittitle", "type": "Name", "value": "Marcel Duchamp with other chess players at the fifth French Championship"}, {"classified_as": [{"id": "aat:folder", "label": "folder", "type": "Type"}], "id": "http://data.duchamparchives.org/pma/archive/container/aspace_381a526771dbdaad2d9f872aa9853423", "type": "Identifier", "value": "15"}], "label": null, "language": [{"id": "aat:300388306", "label": "French (language)", "type": "Type"}], "made_of": [], "ore:isAggregatedBy": null, "part_of": [{"classified_as": [{"id": "aat:file", "label": "file", "type": "Type"}, {"id": "aat:300375748", "label": "archives (groupings)", "type": "Type"}], "id": "http://data.duchamparchives.org/pma/archive/component/aspace_d73511c4869080e6c9b244d7ee45f880", "identified_by": [{"classified_as": [{"id": "aat:300404670", "label": "preferred terms", "type": "Type"}], "id": "http://data.duchamparchives.org/pma/archive/component/aspace_d73511c4869080e6c9b244d7ee45f880/id", "type": "Identifier", "value": "aspace_d73511c4869080e6c9b244d7ee45f880"}, {"classified_as": [{"id": "aat:folder", "label": "folder", "type": "Type"}], "id": "http://data.duchamparchives.org/pma/archive/container/aspace_351a716f33a5c6314d27294a08cab2f7", "type": "Identifier", "value": "15"}, {"id": "http://data.duchamparchives.org/pma/archive/component/aspace_d73511c4869080e6c9b244d7ee45f880/unittitle", "type": "Name", "value": "Unidentified. Chess players at the fifth French championship, including Marcel Duchamp. Chamonix, France"}, {"classified_as": [{"id": "aat:300192339", "label": "sequences", "type": "Type"}], "type": "Identifier", "value": "1"}, {"classified_as": [{"id": "aat:box", "label": "box", "type": "Type"}], "id": "http://data.duchamparchives.org/pma/archive/container/aspace_8bd8b2703afe69b414260dd5a1a3ecc7", "label": "Mixed Materials", "type": "Identifier", "value": "34"}], "part": "http://data.duchamparchives.org/pma/archive/component/MDP_B034_F015_13-1972-9-170", "type": "PhysicalObject"}, {"classified_as": [{"id": "aat:300375748", "label": "archives (groupings)", "type": "Type"}, {"id": "aat:collection", "label": "collection", "type": "Type"}], "id": "http://data.duchamparchives.org/pma/archive/collection/alexina-and-marcel-duchamp-papers", "identified_by": [{"classified_as": [{"id": "aat:300404670", "label": "preferred terms", "type": "Type"}], "id": "_:b512", "type": "Name", "value": "Alexina and Marcel Duchamp Papers"}, {"classified_as": [{"id": "aat:accession", "label": "accession", "type": "Type"}], "id": "_:b513", "type": "Identifier", "value": "MDP"}], "part": ["http://data.duchamparchives.org/pma/archive/component/aspace_s35", "http://data.duchamparchives.org/pma/archive/component/aspace_7c6ebaaaec72196d28f1c93d01cfeb9d", "http://data.duchamparchives.org/pma/archive/component/aspace_s41", "http://data.duchamparchives.org/pma/archive/component/aspace_cc906116872386cfa9ddc663b1565611", "http://data.duchamparchives.org/pma/archive/component/aspace_s85", "http://data.duchamparchives.org/pma/archive/component/aspace_ef40f1f6118ebc31b96ef7c1e040bd7b", "http://data.duchamparchives.org/pma/archive/component/aspace_b9f92ef7f87b9c1d57db4f9d38374ac4", "http://data.duchamparchives.org/pma/archive/component/aspace_2faa1c5bcb46d070f5773fbe8458475a", "http://data.duchamparchives.org/pma/archive/component/aspace_s84", "http://data.duchamparchives.org/pma/archive/component/aspace_af31a1e16b19dec505bdd3bfe2cbad46", "http://data.duchamparchives.org/pma/archive/component/aspace_800c5220c0b9b4a508d9d7522f0882dd", "http://data.duchamparchives.org/pma/archive/component/aspace_2ba57c9dad8b8fd59c806f08f576070b"], "type": "PhysicalObject"}, {"classified_as": [{"id": "aat:series", "label": "series", "type": "Type"}, {"id": "aat:300375748", "label": "archives (groupings)", "type": "Type"}], "id": "http://data.duchamparchives.org/pma/archive/component/aspace_s35", "identified_by": [{"id": "http://data.duchamparchives.org/pma/archive/component/aspace_s35/unittitle", "type": "Name", "value": "Photographs"}, {"classified_as": [{"id": "aat:300404670", "label": "preferred terms", "type": "Type"}], "id": "http://data.duchamparchives.org/pma/archive/component/aspace_s35/id", "type": "Identifier", "value": "aspace_s35"}, {"classified_as": [{"id": "aat:300192339", "label": "sequences", "type": "Type"}], "id": "_:b130", "type": "Identifier", "value": "9"}], "part": ["http://data.duchamparchives.org/pma/archive/component/aspace_ss237", "http://data.duchamparchives.org/pma/archive/component/aspace_b6f06ad0cc029f2e5a7a36a4b101b52f", "http://data.duchamparchives.org/pma/archive/component/aspace_41a430a5631d977cad3f06fb6eda8a13", "http://data.duchamparchives.org/pma/archive/component/aspace_a8aff3d19bda2b650b4b5ce0b11093b0", "http://data.duchamparchives.org/pma/archive/component/aspace_ss235"], "type": "PhysicalObject"}, {"classified_as": [{"id": "aat:subseries", "label": "subseries", "type": "Type"}, {"id": "aat:300375748", "label": "archives (groupings)", "type": "Type"}], "id": "http://data.duchamparchives.org/pma/archive/component/aspace_956d9fa6cc936591d4c4f2b0953eb0ba", "identified_by": [{"id": "http://data.duchamparchives.org/pma/archive/component/aspace_956d9fa6cc936591d4c4f2b0953eb0ba/unittitle", "type": "Name", "value": "Group"}, {"classified_as": [{"id": "aat:300192339", "label": "sequences", "type": "Type"}], "id": "_:b634", "type": "Identifier", "value": "3"}, {"classified_as": [{"id": "aat:300404670", "label": "preferred terms", "type": "Type"}], "id": "http://data.duchamparchives.org/pma/archive/component/aspace_956d9fa6cc936591d4c4f2b0953eb0ba/id", "type": "Identifier", "value": "aspace_956d9fa6cc936591d4c4f2b0953eb0ba"}], "part": ["http://data.duchamparchives.org/pma/archive/component/aspace_d73511c4869080e6c9b244d7ee45f880", "http://data.duchamparchives.org/pma/archive/component/aspace_3fb98cf6be0edba0d19a607f215d3d6a", "http://data.duchamparchives.org/pma/archive/component/aspace_b5a69674f54d9f23360eeb9b85b17fdc", "http://data.duchamparchives.org/pma/archive/component/aspace_e79737e37116d17b9165348736f5e9bc", "http://data.duchamparchives.org/pma/archive/component/aspace_3138d5233aa3bb788a44d71693a5388d", "http://data.duchamparchives.org/pma/archive/component/aspace_473db545fe778024e779bebba86cac04", "http://data.duchamparchives.org/pma/archive/component/aspace_3efe95874f154cb260c5d4b88c52ad59"], "type": "PhysicalObject"}, {"classified_as": [{"id": "aat:subseries", "label": "subseries", "type": "Type"}, {"id": "aat:300375748", "label": "archives (groupings)", "type": "Type"}], "id": "http://data.duchamparchives.org/pma/archive/component/aspace_ss237", "identified_by": [{"id": "http://data.duchamparchives.org/pma/archive/component/aspace_ss237/unittitle", "type": "Name", "value": "Chess"}, {"classified_as": [{"id": "aat:300192339", "label": "sequences", "type": "Type"}], "id": "_:b639", "type": "Identifier", "value": "4"}, {"classified_as": [{"id": "aat:300404670", "label": "preferred terms", "type": "Type"}], "id": "http://data.duchamparchives.org/pma/archive/component/aspace_ss237/id", "type": "Identifier", "value": "aspace_ss237"}], "part": ["http://data.duchamparchives.org/pma/archive/component/aspace_863ab4ea69924a874988c1f6535c8c92", "http://data.duchamparchives.org/pma/archive/component/aspace_181d2f8a3361cceae3acfeaa851a1c00", "http://data.duchamparchives.org/pma/archive/component/aspace_956d9fa6cc936591d4c4f2b0953eb0ba", "http://data.duchamparchives.org/pma/archive/component/aspace_a804ca4b8b19ee99d2c714d95e7847a9"], "type": "PhysicalObject"}], "produced_by": {"carried_out_by": [], "consists_of": [{"carried_out_by": [{"id": "http://data.duchamparchives.org/pma/archive/actor/LCNAF/n80057220", "label": "Duchamp, Marcel, 1887-1968", "type": "Actor"}], "classified_as": [], "id": "http://data.duchamparchives.org/pma/archive/component/aspace_baaafb5813cdff528e1ac5db1497b73a/production/dpc", "technique": [{"id": "aat:300248231", "label": ["depicted", "depictions (visual works)"], "type": "Type"}], "type": "Production"}], "id": "http://data.duchamparchives.org/pma/archive/component/aspace_baaafb5813cdff528e1ac5db1497b73a/production", "timespan": {"begin_of_the_begin": "1927-09-01T00:00:00+00:00", "end_of_the_end": "1927-09-01T00:00:00+00:00", "id": "http://data.duchamparchives.org/pma/archive/component/aspace_baaafb5813cdff528e1ac5db1497b73a/production/timespan", "label": "1927 September", "type": "TimeSpan"}, "took_place_at": [{"id": "tgn:1032562", "label": "Chamonix-Mont-Blanc, France", "type": "Place"}], "type": "Production"}, "referred_to_by": [{"classified_as": ["aat:scopenote"], "id": "http://data.duchamparchives.org/pma/archive/component/aspace_baaafb5813cdff528e1ac5db1497b73a/scope", "type": "LinguisticObject", "value": "&lt;p&gt;Marcel Duchamp with other chess players at the fifth French Championship. Chamonix, France.&lt;/p&gt;"}, {"classified_as": [{"id": "aat:300026687", "label": "acknowledgments", "type": "Type"}], "type": "LinguisticObject", "value": "Gift of Jacqueline, Paul and Peter Matisse in memory of their mother Alexina Duchamp"}, {"classified_as": [{"id": "aat:300266036", "label": "dimensions", "type": "Type"}], "type": "LinguisticObject", "value": "1 photograph"}], "refers_to": [], "related": [], "representation": [{"id": "https://iiif.duchamparchives.org/image/iiif/2/MDP_B034_F015_13-1972-9-170_001", "type": "VisualItem"}, {"id": "https://iiif.duchamparchives.org/image/iiif/2/MDP_B034_F015_13-1972-9-170_002", "type": "VisualItem"}], "subject_of": [], "type": "ManMadeObject", "used_for": []}