{"@context": "https://linked.art/ns/v1/linked-art.json", "about": [], "classified_as": [{"id": "aat:300375748", "label": "archives (groupings)", "type": "Type"}, {"id": "aat:object", "label": "object", "type": "Type"}, {"id": "aat:300127104", "label": "photographic prints", "type": "Type"}], "crm:P104_is_subject_to": [{"classified_as": [{"id": "aat:300417633", "label": "legal status", "type": "Type"}], "id": "_:b12", "type": "crm:E30_Right"}, {"classified_as": [{"id": "aat:300068844", "label": "use", "type": "Type"}], "id": "_:b13", "type": "crm:E30_Right"}], "crm:P57_has_number_of_parts": null, "current_keeper": null, "current_location": {"label": "Philadelphia Museum of Art, Library & Archives", "type": "Place"}, "current_owner": {"id": "http://data.philamuseum.org/", "label": "Philadelphia Museum of Art", "type": "Group"}, "depicts": [], "id": "http://data.duchamparchives.org/pma/archive/component/WLA_B063_F010_003", "identified_by": [{"classified_as": [{"id": "aat:box", "label": "box", "type": "Type"}], "id": "http://data.duchamparchives.org/pma/archive/container/aspace_8a336a351745fa69e65ff4238bd4cb60", "label": "Mixed Materials", "type": "Identifier", "value": "63"}, {"classified_as": [{"id": "aat:accession", "label": "accession", "type": "Type"}], "id": "http://data.duchamparchives.org/pma/archive/component/aspace_b5c2d760a677d07068c34465a9c6f8ef/unitid/0", "type": "Identifier", "value": "WLA_B063_F010_003"}, {"classified_as": [{"id": "aat:folder", "label": "folder", "type": "Type"}], "id": "http://data.duchamparchives.org/pma/archive/container/aspace_a5109d61905046f12ae940041a1636de", "type": "Identifier", "value": "10"}, {"classified_as": [{"id": "aat:300404670", "label": "preferred terms", "type": "Type"}], "id": "http://data.duchamparchives.org/pma/archive/component/aspace_b5c2d760a677d07068c34465a9c6f8ef/id", "type": "Identifier", "value": "aspace_b5c2d760a677d07068c34465a9c6f8ef"}, {"classified_as": [{"id": "aat:300192339", "label": "sequences", "type": "Type"}], "type": "Identifier", "value": "2"}, {"id": "http://data.duchamparchives.org/pma/archive/component/aspace_b5c2d760a677d07068c34465a9c6f8ef/unittitle", "type": "Name", "value": "Installation photograph of the \"Pre-Columbian Art of the Andean Area\" exhibition"}], "label": null, "language": [{"id": "aat:300388277", "label": "English (language)", "type": "Type"}], "made_of": [], "ore:isAggregatedBy": null, "part_of": [{"classified_as": [{"id": "aat:300375748", "label": "archives (groupings)", "type": "Type"}, {"id": "aat:collection", "label": "collection", "type": "Type"}], "id": "http://data.duchamparchives.org/pma/archive/collection/arensberg-archives", "identified_by": [{"classified_as": [{"id": "aat:300404670", "label": "preferred terms", "type": "Type"}], "id": "_:b280", "type": "Name", "value": "Arensberg Archives"}, {"classified_as": [{"id": "aat:accession", "label": "accession", "type": "Type"}], "id": "_:b281", "type": "Identifier", "value": "WLA"}], "part": ["http://data.duchamparchives.org/pma/archive/component/aspace_e4b0fabbfcf6fc758c1f80e7c72c95cb", "http://data.duchamparchives.org/pma/archive/component/aspace_949425b7b40368328802306e60552883", "http://data.duchamparchives.org/pma/archive/component/aspace_11b93f48a87f733e6a6d11acc0ee9fb5", "http://data.duchamparchives.org/pma/archive/component/aspace_s5", "http://data.duchamparchives.org/pma/archive/component/aspace_71bf3f73043da1328a2b3ed316cd69bb", "http://data.duchamparchives.org/pma/archive/component/aspace_s1", "http://data.duchamparchives.org/pma/archive/component/aspace_s7", "http://data.duchamparchives.org/pma/archive/component/aspace_d9515f0104d280eeecdc5e6883112ef0", "http://data.duchamparchives.org/pma/archive/component/aspace_s3"], "type": "PhysicalObject"}, {"classified_as": [{"id": "aat:300375748", "label": "archives (groupings)", "type": "Type"}, {"id": "aat:file", "label": "file", "type": "Type"}], "id": "http://data.duchamparchives.org/pma/archive/component/aspace_ae04785d5fc86ae0414eaf9f8ea72694", "identified_by": [{"classified_as": [{"id": "aat:300404670", "label": "preferred terms", "type": "Type"}], "id": "http://data.duchamparchives.org/pma/archive/component/aspace_ae04785d5fc86ae0414eaf9f8ea72694/id", "type": "Identifier", "value": "aspace_ae04785d5fc86ae0414eaf9f8ea72694"}, {"id": "http://data.duchamparchives.org/pma/archive/component/aspace_ae04785d5fc86ae0414eaf9f8ea72694/unittitle", "type": "Name", "value": "University of California, Berkeley. \"Pre-Columbian Art of the Andean Area\""}, {"classified_as": [{"id": "aat:box", "label": "box", "type": "Type"}], "id": "http://data.duchamparchives.org/pma/archive/container/aspace_1ea2b9a3c6b7f5cf64698285e9383585", "label": "Mixed Materials", "type": "Identifier", "value": "63"}, {"classified_as": [{"id": "aat:300192339", "label": "sequences", "type": "Type"}], "id": "_:b289", "type": "Identifier", "value": "9"}, {"classified_as": [{"id": "aat:folder", "label": "folder", "type": "Type"}], "id": "http://data.duchamparchives.org/pma/archive/container/aspace_a957a570f9935381fc2562582cb99c30", "type": "Identifier", "value": "10"}], "part": ["http://data.duchamparchives.org/pma/archive/component/WLA_B063_F010_022", "http://data.duchamparchives.org/pma/archive/component/WLA_B063_F010_005", "http://data.duchamparchives.org/pma/archive/component/WLA_B063_F010_014", "http://data.duchamparchives.org/pma/archive/component/WLA_B063_F010_021", "http://data.duchamparchives.org/pma/archive/component/WLA_B063_F010_027", "http://data.duchamparchives.org/pma/archive/component/WLA_B063_F010_007", "http://data.duchamparchives.org/pma/archive/component/WLA_B063_F010_002", "http://data.duchamparchives.org/pma/archive/component/WLA_B063_F010_019", "http://data.duchamparchives.org/pma/archive/component/WLA_B063_F010_015", "http://data.duchamparchives.org/pma/archive/component/WLA_B063_F010_011", "http://data.duchamparchives.org/pma/archive/component/WLA_B063_F010_017", "http://data.duchamparchives.org/pma/archive/component/WLA_B063_F010_001", "http://data.duchamparchives.org/pma/archive/component/WLA_B063_F010_026", "http://data.duchamparchives.org/pma/archive/component/WLA_B063_F010_010", "http://data.duchamparchives.org/pma/archive/component/WLA_B063_F010_012", "http://data.duchamparchives.org/pma/archive/component/WLA_B063_F010_009", "http://data.duchamparchives.org/pma/archive/component/WLA_B063_F010_016", "http://data.duchamparchives.org/pma/archive/component/WLA_B063_F010_025", "http://data.duchamparchives.org/pma/archive/component/WLA_B063_F010_020", "http://data.duchamparchives.org/pma/archive/component/WLA_B063_F010_023", "http://data.duchamparchives.org/pma/archive/component/WLA_B063_F010_006", "http://data.duchamparchives.org/pma/archive/component/WLA_B063_F010_024", "http://data.duchamparchives.org/pma/archive/component/WLA_B063_F010_008", "http://data.duchamparchives.org/pma/archive/component/WLA_B063_F010_018", "http://data.duchamparchives.org/pma/archive/component/WLA_B063_F010_013", "http://data.duchamparchives.org/pma/archive/component/WLA_B063_F010_004", "http://data.duchamparchives.org/pma/archive/component/WLA_B063_F010_003"], "type": "PhysicalObject"}, {"classified_as": [{"id": "aat:300375748", "label": "archives (groupings)", "type": "Type"}, {"id": "aat:subseries", "label": "subseries", "type": "Type"}], "id": "http://data.duchamparchives.org/pma/archive/component/aspace_973ccca630d61cdac593cd585611e8f5", "identified_by": [{"id": "http://data.duchamparchives.org/pma/archive/component/aspace_973ccca630d61cdac593cd585611e8f5/unittitle", "type": "Name", "value": "Exhibitions"}, {"classified_as": [{"id": "aat:300404670", "label": "preferred terms", "type": "Type"}], "id": "http://data.duchamparchives.org/pma/archive/component/aspace_973ccca630d61cdac593cd585611e8f5/id", "type": "Identifier", "value": "aspace_973ccca630d61cdac593cd585611e8f5"}, {"classified_as": [{"id": "aat:300192339", "label": "sequences", "type": "Type"}], "id": "_:b459", "type": "Identifier", "value": "7"}], "part": ["http://data.duchamparchives.org/pma/archive/component/aspace_820adbacda749f7cc00ab6d5a38e6bc3", "http://data.duchamparchives.org/pma/archive/component/aspace_0d1ffcebb121d62a8dac4bc27f7597f8", "http://data.duchamparchives.org/pma/archive/component/aspace_b7c4124ce40278f814cedce1274fd621", "http://data.duchamparchives.org/pma/archive/component/aspace_d1302b74336a068821fca88610e4282a", "http://data.duchamparchives.org/pma/archive/component/aspace_4954ddeef0e3a340750a1c67453e831b", "http://data.duchamparchives.org/pma/archive/component/aspace_08615d150ceb8fbc6ba7ddec3d7d4dc7", "http://data.duchamparchives.org/pma/archive/component/aspace_b7e550092df835014347b769fe66c08d", "http://data.duchamparchives.org/pma/archive/component/aspace_057d275063096f05500d371d4af6f801", "http://data.duchamparchives.org/pma/archive/component/aspace_792720fb7945f93c1bb4d16383b61bf8", "http://data.duchamparchives.org/pma/archive/component/aspace_36758bda2d1d994cfc5aba84295e4068", "http://data.duchamparchives.org/pma/archive/component/aspace_9d284e63774d229670bb96be3f77cd99", "http://data.duchamparchives.org/pma/archive/component/aspace_522c05e995d45fccf693024420342d7c", "http://data.duchamparchives.org/pma/archive/component/aspace_401a1f60cb5083b8a25f4cf0d2a7292a", "http://data.duchamparchives.org/pma/archive/component/aspace_ae04785d5fc86ae0414eaf9f8ea72694", "http://data.duchamparchives.org/pma/archive/component/aspace_614cd3159270fe4d276e3d420e286fd0", "http://data.duchamparchives.org/pma/archive/component/aspace_effe09b1b211be9b7577523643d14ea2"], "type": "PhysicalObject"}, {"classified_as": [{"id": "aat:series", "label": "series", "type": "Type"}, {"id": "aat:300375748", "label": "archives (groupings)", "type": "Type"}], "id": "http://data.duchamparchives.org/pma/archive/component/aspace_s3", "identified_by": [{"id": "http://data.duchamparchives.org/pma/archive/component/aspace_s3/unittitle", "type": "Name", "value": "Photographs"}, {"classified_as": [{"id": "aat:300192339", "label": "sequences", "type": "Type"}], "id": "_:b112", "type": "Identifier", "value": "7"}, {"classified_as": [{"id": "aat:300404670", "label": "preferred terms", "type": "Type"}], "id": "http://data.duchamparchives.org/pma/archive/component/aspace_s3/id", "type": "Identifier", "value": "aspace_s3"}], "part": ["http://data.duchamparchives.org/pma/archive/component/aspace_43edc58ea25ee555fdc9292d494552cc", "http://data.duchamparchives.org/pma/archive/component/aspace_ss3", "http://data.duchamparchives.org/pma/archive/component/aspace_ss7", "http://data.duchamparchives.org/pma/archive/component/aspace_1f88108d7ba960ce251d843ea3c5fc8c", "http://data.duchamparchives.org/pma/archive/component/aspace_ss12", "http://data.duchamparchives.org/pma/archive/component/aspace_973ccca630d61cdac593cd585611e8f5", "http://data.duchamparchives.org/pma/archive/component/aspace_5b1b6ae4be44cff58ebf34b471a7db60", "http://data.duchamparchives.org/pma/archive/component/aspace_65e824a99c761887b2bd95f67d9d9fcc", "http://data.duchamparchives.org/pma/archive/component/aspace_1fdc314a176136c4dea19eb8ec59240f", "http://data.duchamparchives.org/pma/archive/component/aspace_f9cb9942b5db04fad39660c208daf76f", "http://data.duchamparchives.org/pma/archive/component/aspace_0139385e6cf0a22effdc7336bce6577c"], "type": "PhysicalObject"}], "produced_by": {"carried_out_by": [], "consists_of": [{"carried_out_by": [{"id": "http://data.duchamparchives.org/pma/archive/actor/LCNAF/n79046084", "label": "University of California, Berkeley", "type": "Actor"}], "classified_as": [], "id": "http://data.duchamparchives.org/pma/archive/component/aspace_b5c2d760a677d07068c34465a9c6f8ef/production/dpc", "technique": [{"id": "aat:300248231", "label": ["depicted", "depictions (visual works)"], "type": "Type"}], "type": "Production"}], "id": "http://data.duchamparchives.org/pma/archive/component/aspace_b5c2d760a677d07068c34465a9c6f8ef/production", "timespan": {"begin_of_the_begin": "1948-01-01T00:00:00+00:00", "end_of_the_end": "1948-01-01T00:00:00+00:00", "id": "http://data.duchamparchives.org/pma/archive/component/aspace_b5c2d760a677d07068c34465a9c6f8ef/production/timespan", "label": "1948", "type": "TimeSpan"}, "took_place_at": [{"id": "tgn:7013386", "label": "Berkeley, United States", "type": "Place"}], "type": "Production"}, "referred_to_by": [{"classified_as": ["aat:scopenote"], "id": "http://data.duchamparchives.org/pma/archive/component/aspace_b5c2d760a677d07068c34465a9c6f8ef/scope", "type": "LinguisticObject", "value": "&lt;p&gt;Installation photograph of the \"Pre-Columbian Art of the Andean Area\" exhibition at University of California, Berkeley.&lt;/p&gt;"}, {"classified_as": [{"id": "aat:300266036", "label": "dimensions", "type": "Type"}], "type": "LinguisticObject", "value": "1 photograph"}], "refers_to": [], "related": [], "representation": [{"id": "https://iiif.duchamparchives.org/image/iiif/2/WLA_B063_F010_003_001", "type": "VisualItem"}], "subject_of": [], "type": "ManMadeObject", "used_for": []}